lektor_git_timestamp-1.0.0.dist-info/METADATA
lektor_git_timestamp-1.0.0.dist-info/WHEEL
lektor_git_timestamp-1.0.0.dist-info/entry_points.txt
lektor_git_timestamp-1.0.0.dist-info/licenses/LICENSE
lektor_git_timestamp.py
lektor_git_timestamp-1.0.0.dist-info/RECORD
