Metadata-Version: 2.1
Name: lektor-git-timestamp
Version: 1.0.0
Summary: Lektor type to deduce page modification time from git
Keywords: Lektor plugin
Author-Email: Jeff Dairiki <dairiki@dairiki.org>
License: Copyright © 2020, 2021, 2023 Geoffrey T. Dairiki
Classifier: Development Status :: 5 - Production/Stable
Classifier: Environment :: Plugins
Classifier: Environment :: Web Environment
Classifier: Framework :: Lektor
Classifier: Intended Audience :: Developers
Classifier: License :: OSI Approved :: MIT License
Classifier: Programming Language :: Python :: 3
Classifier: Programming Language :: Python :: 3.8
Classifier: Programming Language :: Python :: 3.9
Classifier: Programming Language :: Python :: 3.10
Classifier: Programming Language :: Python :: 3.11
Classifier: Programming Language :: Python :: 3.12
Classifier: Topic :: Software Development :: Version Control :: Git
Classifier: Topic :: Text Processing
Project-URL: Home, https://github.com/dairiki/lektor-git-timestamp
Requires-Python: >=3.8
Requires-Dist: lektorlib>=1.2.1
